README.md
setup.py
dnbpy/__init__.py
dnbpy/box.py
dnbpy/duel.py
dnbpy/game.py
dnbpy/level1_heuristic_policy.py
dnbpy/level2_heuristic_policy.py
dnbpy/level3_minimax_policy.py
dnbpy/mcts_policy.py
dnbpy/misc_functions.py
dnbpy/play.py
dnbpy/policy.py
dnbpy/random_policy.py
dnbpy/strings_and_coins.py
dnbpy/to_string.py
dnbpy.egg-info/PKG-INFO
dnbpy.egg-info/SOURCES.txt
dnbpy.egg-info/dependency_links.txt
dnbpy.egg-info/top_level.txt